clevertable/Binary.py
clevertable/Const.py
clevertable/ConversionProfile.py
clevertable/Converter.py
clevertable/DataFrameProfile.py
clevertable/Enumerate.py
clevertable/Flatten.py
clevertable/Float.py
clevertable/ForEach.py
clevertable/Function.py
clevertable/Id.py
clevertable/Ignore.py
clevertable/Infer.py
clevertable/Label.py
clevertable/List.py
clevertable/Map.py
clevertable/OneHot.py
clevertable/Parallel.py
clevertable/Pipeline.py
clevertable/RecordProfile.py
clevertable/Split.py
clevertable/StrictFunction.py
clevertable/Strip.py
clevertable/Transpose.py
clevertable/Try.py
clevertable/__init__.py
clevertable/__main__.py
clevertable/_utils.py
clevertable-3.1.0.dist-info/LICENSE
clevertable-3.1.0.dist-info/METADATA
clevertable-3.1.0.dist-info/WHEEL
clevertable-3.1.0.dist-info/entry_points.txt
clevertable-3.1.0.dist-info/top_level.txt
clevertable-3.1.0.dist-info/RECORD
