Metadata-Version: 2.1
Name: clevertable
Version: 3.1.0
Summary: Low effort conversion of tabular data into numerical values.
Author: Tom Mohr
License: MIT License
Project-URL: Homepage, https://github.com/tom-mohr/clevertable
Keywords: parser,converter,numerical
Classifier: License :: OSI Approved :: MIT License
Classifier: Programming Language :: Python
Classifier: Programming Language :: Python :: 3
Requires-Python: >=3.9
License-File: LICENSE
Requires-Dist: numpy
Requires-Dist: pandas
Requires-Dist: openpyxl
Provides-Extra: dev
Requires-Dist: bumpver ; extra == 'dev'
Requires-Dist: build ; extra == 'dev'
Requires-Dist: twine ; extra == 'dev'
Requires-Dist: pytest ; extra == 'dev'
